codemod_yaml/__init__.py
codemod_yaml/_version.py
codemod_yaml/base.py
codemod_yaml/cyq.py
codemod_yaml/items.py
codemod_yaml/parser.py
codemod_yaml/py.typed
codemod_yaml/string_repr.py
codemod_yaml/style.py
codemod_yaml-0.7.0.dist-info/licenses/LICENSE
codemod_yaml-0.7.0.dist-info/METADATA
codemod_yaml-0.7.0.dist-info/WHEEL
codemod_yaml-0.7.0.dist-info/entry_points.txt
codemod_yaml-0.7.0.dist-info/top_level.txt
codemod_yaml-0.7.0.dist-info/RECORD
