Metadata-Version: 2.4
Name: codemod-yaml
Version: 0.7.0
Summary: Lib to modify yaml inplace
Home-page: https://github.com/advice-animal/codemod-yaml/
Author: Tim Hatch
Author-email: tim@timhatch.com
License: MIT
Requires-Python: >=3.9
License-File: LICENSE
Requires-Dist: tree-sitter>=0.23.2
Requires-Dist: tree-sitter-yaml>=0.6.0
Provides-Extra: demo
Requires-Dist: moreorless; extra == "demo"
Provides-Extra: dev
Requires-Dist: ruff==0.8.0; extra == "dev"
Requires-Dist: checkdeps==0.9.0; extra == "dev"
Requires-Dist: mypy==1.13.0; extra == "dev"
Requires-Dist: tox==4.23.2; extra == "dev"
Provides-Extra: test
Requires-Dist: coverage>=6; extra == "test"
Requires-Dist: pytest; extra == "test"
Requires-Dist: pytest-cov; extra == "test"
Requires-Dist: moreorless; extra == "test"
Requires-Dist: pyyaml; extra == "test"
Dynamic: license-file
